magictype/__init__.py
magictype/magictype.py
magictype/requirements.txt
magictype-0.3.0.dist-info/METADATA
magictype-0.3.0.dist-info/WHEEL
magictype-0.3.0.dist-info/RECORD
