Metadata-Version: 2.1
Name: magictype
Version: 0.3.0
Summary: generate type hints using magic
License: MIT
Author: franzkurt
Author-email: franz.gastring@gmail.com
Requires-Python: >=3.11,<4.0
Classifier: License :: OSI Approved :: MIT License
Classifier: Programming Language :: Python :: 3
Classifier: Programming Language :: Python :: 3.11
Classifier: Programming Language :: Python :: 3.12
